{
  "columns": [
    {
      "columnName": "env_ver",
      "isMandatory": true,
      "horizontalAlignment": "General",
      "verticalAlignment": "Bottom",
      "columnWidth": 90,
      "indentLevel": 0,
      "style": "Normal",
      "numberFormat": "General",
      "visible": false,
      "autosizeColumn": false,
      "searchFor": "",
      "replaceWith": ""
    },
    {
      "columnName": "env_name",
      "isMandatory": true,
      "horizontalAlignment": "General",
      "verticalAlignment": "Bottom",
      "columnWidth": 90,
      "indentLevel": 0,
      "style": "Normal",
      "numberFormat": "General",
      "visible": false,
      "autosizeColumn": false,
      "searchFor": "",
      "replaceWith": ""
    },
    {
      "columnName": "env_time",
      "isMandatory": true,
      "horizontalAlignment": "General",
      "verticalAlignment": "Bottom",
      "columnWidth": 90,
      "indentLevel": 0,
      "style": "Normal",
      "numberFormat": "\"yyyy\"-\"mm\"-\"dd HH:mm:ss\".000",
      "visible": true,
      "autosizeColumn": false,
      "searchFor": "",
      "replaceWith": ""
    },
    {
      "columnName": "env_epoch",
      "isMandatory": true,
      "horizontalAlignment": "General",
      "verticalAlignment": "Bottom",
      "columnWidth": 90,
      "indentLevel": 0,
      "style": "Normal",
      "numberFormat": "General",
      "visible": false,
      "autosizeColumn": false,
      "searchFor": "",
      "replaceWith": ""
    },
    {
      "columnName": "env_seqNum",
      "isMandatory": true,
      "horizontalAlignment": "General",
      "verticalAlignment": "Bottom",
      "columnWidth": 90,
      "indentLevel": 0,
      "style": "Normal",
      "numberFormat": "General",
      "visible": false,
      "autosizeColumn": false,
      "searchFor": "",
      "replaceWith": ""
    },
    {
      "columnName": "env_popSample",
      "isMandatory": true,
      "horizontalAlignment": "General",
      "verticalAlignment": "Bottom",
      "columnWidth": 91.5,
      "indentLevel": 0,
      "style": "Normal",
      "numberFormat": "#,##0.00",
      "visible": false,
      "autosizeColumn": false,
      "searchFor": "",
      "replaceWith": ""
    },
    {
      "columnName": "env_iKey",
      "isMandatory": true,
      "horizontalAlignment": "General",
      "verticalAlignment": "Bottom",
      "columnWidth": 90,
      "indentLevel": 0,
      "style": "Normal",
      "numberFormat": "General",
      "visible": false,
      "autosizeColumn": false,
      "searchFor": "",
      "replaceWith": ""
    },
    {
      "columnName": "env_flags",
      "isMandatory": true,
      "horizontalAlignment": "General",
      "verticalAlignment": "Bottom",
      "columnWidth": 90,
      "indentLevel": 0,
      "style": "Normal",
      "numberFormat": "General",
      "visible": false,
      "autosizeColumn": false,
      "searchFor": "",
      "replaceWith": ""
    },
    {
      "columnName": "env_cv",
      "isMandatory": true,
      "horizontalAlignment": "General",
      "verticalAlignment": "Bottom",
      "columnWidth": 90,
      "indentLevel": 0,
      "style": "Normal",
      "numberFormat": "General",
      "visible": false,
      "autosizeColumn": false,
      "searchFor": "",
      "replaceWith": ""
    },
    {
      "columnName": "env_os",
      "isMandatory": true,
      "horizontalAlignment": "General",
      "verticalAlignment": "Bottom",
      "columnWidth": 90,
      "indentLevel": 0,
      "style": "Normal",
      "numberFormat": "General",
      "visible": false,
      "autosizeColumn": false,
      "searchFor": "",
      "replaceWith": ""
    },
    {
      "columnName": "env_osVer",
      "isMandatory": true,
      "horizontalAlignment": "General",
      "verticalAlignment": "Bottom",
      "columnWidth": 90,
      "indentLevel": 0,
      "style": "Normal",
      "numberFormat": "General",
      "visible": false,
      "autosizeColumn": false,
      "searchFor": "",
      "replaceWith": ""
    },
    {
      "columnName": "env_appId",
      "isMandatory": true,
      "horizontalAlignment": "General",
      "verticalAlignment": "Bottom",
      "columnWidth": 90,
      "indentLevel": 0,
      "style": "Normal",
      "numberFormat": "General",
      "visible": false,
      "autosizeColumn": false,
      "searchFor": "",
      "replaceWith": ""
    },
    {
      "columnName": "env_appVer",
      "isMandatory": true,
      "horizontalAlignment": "General",
      "verticalAlignment": "Bottom",
      "columnWidth": 90,
      "indentLevel": 0,
      "style": "Normal",
      "numberFormat": "General",
      "visible": false,
      "autosizeColumn": false,
      "searchFor": "",
      "replaceWith": ""
    },
    {
      "columnName": "env_cloud_ver",
      "isMandatory": true,
      "horizontalAlignment": "General",
      "verticalAlignment": "Bottom",
      "columnWidth": 90,
      "indentLevel": 0,
      "style": "Normal",
      "numberFormat": "General",
      "visible": false,
      "autosizeColumn": false,
      "searchFor": "",
      "replaceWith": ""
    },
    {
      "columnName": "env_cloud_name",
      "isMandatory": true,
      "horizontalAlignment": "General",
      "verticalAlignment": "Bottom",
      "columnWidth": 96,
      "indentLevel": 0,
      "style": "Normal",
      "numberFormat": "General",
      "visible": false,
      "autosizeColumn": false,
      "searchFor": "",
      "replaceWith": ""
    },
    {
      "columnName": "env_cloud_role",
      "isMandatory": true,
      "horizontalAlignment": "General",
      "verticalAlignment": "Bottom",
      "columnWidth": 90,
      "indentLevel": 0,
      "style": "Normal",
      "numberFormat": "General",
      "visible": false,
      "autosizeColumn": false,
      "searchFor": "",
      "replaceWith": ""
    },
    {
      "columnName": "env_cloud_roleVer",
      "isMandatory": true,
      "horizontalAlignment": "General",
      "verticalAlignment": "Bottom",
      "columnWidth": 105,
      "indentLevel": 0,
      "style": "Normal",
      "numberFormat": "General",
      "visible": false,
      "autosizeColumn": false,
      "searchFor": "",
      "replaceWith": ""
    },
    {
      "columnName": "env_cloud_roleInstance",
      "isMandatory": true,
      "horizontalAlignment": "General",
      "verticalAlignment": "Bottom",
      "columnWidth": 127.5,
      "indentLevel": 0,
      "style": "Normal",
      "numberFormat": "General",
      "visible": false,
      "autosizeColumn": false,
      "searchFor": "",
      "replaceWith": ""
    },
    {
      "columnName": "env_cloud_environment",
      "isMandatory": true,
      "horizontalAlignment": "General",
      "verticalAlignment": "Bottom",
      "columnWidth": 130.5,
      "indentLevel": 0,
      "style": "Normal",
      "numberFormat": "General",
      "visible": false,
      "autosizeColumn": false,
      "searchFor": "",
      "replaceWith": ""
    },
    {
      "columnName": "env_cloud_location",
      "isMandatory": true,
      "horizontalAlignment": "General",
      "verticalAlignment": "Bottom",
      "columnWidth": 107.25,
      "indentLevel": 0,
      "style": "Normal",
      "numberFormat": "General",
      "visible": false,
      "autosizeColumn": false,
      "searchFor": "",
      "replaceWith": ""
    },
    {
      "columnName": "env_cloud_deploymentUnit",
      "isMandatory": true,
      "horizontalAlignment": "General",
      "verticalAlignment": "Bottom",
      "columnWidth": 147,
      "indentLevel": 0,
      "style": "Normal",
      "numberFormat": "General",
      "visible": false,
      "autosizeColumn": false,
      "searchFor": "",
      "replaceWith": ""
    },
    {
      "columnName": "activityId",
      "isMandatory": true,
      "horizontalAlignment": "General",
      "verticalAlignment": "Bottom",
      "columnWidth": 90,
      "indentLevel": 0,
      "style": "Normal",
      "numberFormat": "General",
      "visible": false,
      "autosizeColumn": false,
      "searchFor": "",
      "replaceWith": ""
    },
    {
      "columnName": "operationId",
      "isMandatory": true,
      "horizontalAlignment": "General",
      "verticalAlignment": "Bottom",
      "columnWidth": 90,
      "indentLevel": 0,
      "style": "Normal",
      "numberFormat": "General",
      "visible": false,
      "autosizeColumn": false,
      "searchFor": "",
      "replaceWith": ""
    },
    {
      "columnName": "ClientRequestId",
      "isMandatory": true,
      "horizontalAlignment": "General",
      "verticalAlignment": "Bottom",
      "columnWidth": 241.5,
      "indentLevel": 1,
      "style": "Normal",
      "numberFormat": "General",
      "visible": true,
      "autosizeColumn": false,
      "searchFor": "",
      "replaceWith": ""
    },
    {
      "columnName": "ServerRequestId",
      "isMandatory": true,
      "horizontalAlignment": "General",
      "verticalAlignment": "Bottom",
      "columnWidth": 243.75,
      "indentLevel": 1,
      "style": "Normal",
      "numberFormat": "General",
      "visible": true,
      "autosizeColumn": false,
      "searchFor": "",
      "replaceWith": ""
    },
    {
      "columnName": "Command",
      "isMandatory": true,
      "horizontalAlignment": "General",
      "verticalAlignment": "Bottom",
      "columnWidth": 90,
      "indentLevel": 0,
      "style": "Normal",
      "numberFormat": "General",
      "visible": false,
      "autosizeColumn": false,
      "searchFor": "",
      "replaceWith": ""
    },
    {
      "columnName": "OrganizationId",
      "isMandatory": true,
      "horizontalAlignment": "General",
      "verticalAlignment": "Bottom",
      "columnWidth": 180,
      "indentLevel": 0,
      "style": "Normal",
      "numberFormat": "General",
      "visible": true,
      "autosizeColumn": false,
      "searchFor": "",
      "replaceWith": ""
    },
    {
      "columnName": "MailboxGuid",
      "isMandatory": true,
      "horizontalAlignment": "General",
      "verticalAlignment": "Bottom",
      "columnWidth": 90,
      "indentLevel": 0,
      "style": "Normal",
      "numberFormat": "General",
      "visible": false,
      "autosizeColumn": false,
      "searchFor": "",
      "replaceWith": ""
    },
    {
      "columnName": "FolderId",
      "isMandatory": true,
      "horizontalAlignment": "General",
      "verticalAlignment": "Bottom",
      "columnWidth": 90,
      "indentLevel": 0,
      "style": "Normal",
      "numberFormat": "General",
      "visible": false,
      "autosizeColumn": false,
      "searchFor": "",
      "replaceWith": ""
    },
    {
      "columnName": "InputKey",
      "isMandatory": true,
      "horizontalAlignment": "General",
      "verticalAlignment": "Bottom",
      "columnWidth": 90,
      "indentLevel": 0,
      "style": "Normal",
      "numberFormat": "General",
      "visible": false,
      "autosizeColumn": false,
      "searchFor": "",
      "replaceWith": ""
    },
    {
      "columnName": "AppId",
      "isMandatory": true,
      "horizontalAlignment": "General",
      "verticalAlignment": "Bottom",
      "columnWidth": 90,
      "indentLevel": 0,
      "style": "Normal",
      "numberFormat": "General",
      "visible": false,
      "autosizeColumn": false,
      "searchFor": "",
      "replaceWith": ""
    },
    {
      "columnName": "ClientInfoString",
      "isMandatory": true,
      "horizontalAlignment": "General",
      "verticalAlignment": "Bottom",
      "columnWidth": 290,
      "indentLevel": 0,
      "style": "Normal",
      "numberFormat": "General",
      "visible": false,
      "autosizeColumn": true,
      "searchFor": "",
      "replaceWith": ""
    },
    {
      "columnName": "ErrorCode",
      "isMandatory": true,
      "horizontalAlignment": "General",
      "verticalAlignment": "Bottom",
      "columnWidth": 90,
      "indentLevel": 0,
      "style": "Normal",
      "numberFormat": "General",
      "visible": true,
      "autosizeColumn": false,
      "searchFor": "",
      "replaceWith": ""
    },
    {
      "columnName": "Exception",
      "isMandatory": true,
      "horizontalAlignment": "General",
      "verticalAlignment": "Bottom",
      "columnWidth": 290,
      "indentLevel": 0,
      "style": "Normal",
      "numberFormat": "General",
      "visible": true,
      "autosizeColumn": false,
      "searchFor": "",
      "replaceWith": ""
    },
    {
      "columnName": "InputData",
      "isMandatory": true,
      "horizontalAlignment": "General",
      "verticalAlignment": "Bottom",
      "columnWidth": 90,
      "indentLevel": 0,
      "style": "Normal",
      "numberFormat": "General",
      "visible": false,
      "autosizeColumn": false,
      "searchFor": "",
      "replaceWith": ""
    },
    {
      "columnName": "CustomData",
      "isMandatory": true,
      "horizontalAlignment": "General",
      "verticalAlignment": "Bottom",
      "columnWidth": 90,
      "indentLevel": 0,
      "style": "Normal",
      "numberFormat": "General",
      "visible": true,
      "autosizeColumn": false,
      "searchFor": "",
      "replaceWith": ""
    },
    {
      "columnName": "Latency",
      "isMandatory": true,
      "horizontalAlignment": "General",
      "verticalAlignment": "Bottom",
      "columnWidth": 90,
      "indentLevel": 0,
      "style": "Normal",
      "numberFormat": "General",
      "visible": true,
      "autosizeColumn": false,
      "searchFor": "",
      "replaceWith": ""
    },
    {
      "columnName": "SourceNamespace",
      "isMandatory": true,
      "horizontalAlignment": "General",
      "verticalAlignment": "Bottom",
      "columnWidth": 102,
      "indentLevel": 0,
      "style": "Normal",
      "numberFormat": "General",
      "visible": false,
      "autosizeColumn": false,
      "searchFor": "",
      "replaceWith": ""
    },
    {
      "columnName": "SourceMoniker",
      "isMandatory": true,
      "horizontalAlignment": "General",
      "verticalAlignment": "Bottom",
      "columnWidth": 90,
      "indentLevel": 0,
      "style": "Normal",
      "numberFormat": "General",
      "visible": false,
      "autosizeColumn": false,
      "searchFor": "",
      "replaceWith": ""
    },
    {
      "columnName": "SourceVersion",
      "isMandatory": true,
      "horizontalAlignment": "General",
      "verticalAlignment": "Bottom",
      "columnWidth": 90,
      "indentLevel": 0,
      "style": "Normal",
      "numberFormat": "General",
      "visible": false,
      "autosizeColumn": false,
      "searchFor": "",
      "replaceWith": ""
    },
    {
      "columnName": "LogonType",
      "isMandatory": true,
      "horizontalAlignment": "General",
      "verticalAlignment": "Bottom",
      "columnWidth": 90,
      "indentLevel": 0,
      "style": "Normal",
      "numberFormat": "General",
      "visible": true,
      "autosizeColumn": false,
      "searchFor": "",
      "replaceWith": ""
    },
    {
      "columnName": "ShortClientInfoString",
      "isMandatory": true,
      "horizontalAlignment": "General",
      "verticalAlignment": "Bottom",
      "columnWidth": 114.75,
      "indentLevel": 1,
      "style": "Normal",
      "numberFormat": "General",
      "visible": true,
      "autosizeColumn": false,
      "searchFor": "",
      "replaceWith": ""
    },
    {
      "columnName": "ResultCategory",
      "isMandatory": true,
      "horizontalAlignment": "General",
      "verticalAlignment": "Bottom",
      "columnWidth": 90,
      "indentLevel": 0,
      "style": "Normal",
      "numberFormat": "General",
      "visible": true,
      "autosizeColumn": false,
      "searchFor": "",
      "replaceWith": ""
    },
    {
      "columnName": "buildVersion",
      "isMandatory": true,
      "horizontalAlignment": "General",
      "verticalAlignment": "Bottom",
      "columnWidth": 90,
      "indentLevel": 0,
      "style": "Normal",
      "numberFormat": "General",
      "visible": false,
      "autosizeColumn": false,
      "searchFor": "",
      "replaceWith": ""
    },
    {
      "columnName": "__AuthType__",
      "isMandatory": true,
      "horizontalAlignment": "General",
      "verticalAlignment": "Bottom",
      "columnWidth": 90,
      "indentLevel": 0,
      "style": "Normal",
      "numberFormat": "General",
      "visible": false,
      "autosizeColumn": false,
      "searchFor": "",
      "replaceWith": ""
    },
    {
      "columnName": "__AuthIdentity__",
      "isMandatory": true,
      "horizontalAlignment": "General",
      "verticalAlignment": "Bottom",
      "columnWidth": 96.75,
      "indentLevel": 0,
      "style": "Normal",
      "numberFormat": "General",
      "visible": false,
      "autosizeColumn": false,
      "searchFor": "",
      "replaceWith": ""
    }
  ],
  "conditionalFormats": [
    {
      "FriendlyName": "LogonType Cell Value =Owner",
      "ColumnName": "LogonType",
      "CountOccurrences": false,
      "WarnIfOccurrencesGTZero": false,
      "Type": "ConstainsText",
      "Style": "Normal",
      "FontColor": "#006100",
      "FillColor": "#C6EFCE",
      "ColorScaleColorMinimum": null,
      "ColorScaleColorMaximum": null,
      "ContainsTextSearch": "Owner",
      "ContainsTextOperator": "Contains",
      "CellValueFormula1": null,
      "CellValueFormula2": null,
      "CellValueOperator": null,
      "CustomFormula": null
    },
    {  
        "FriendlyName": "Latency Color Scale #C65911 Down to #A9D08E",
        "ColumnName": "Latency",
        "CountOccurrences": false,
        "WarnIfOccurrencesGTZero": false,
        "Type": "ColorScale",
        "Style": "Normal",
        "FontColor": null,
        "FillColor": null,
        "ColorScaleColorMinimum": "#A9D08E",
        "ColorScaleColorMaximum": "#C65911",
        "ContainsTextSearch": null,
        "ContainsTextOperator": null,
        "CellValueFormula1": null,
        "CellValueFormula2": null,
        "CellValueOperator": null,
        "CustomFormula": null
      },
      {
        "FriendlyName": "ShortClientInfoString Contains Text CalendarRepairAssistant",
        "ColumnName": "ShortClientInfoString",
        "CountOccurrences": false,
        "WarnIfOccurrencesGTZero": false,
        "Type": "ConstainsText",
        "Style": "Normal",
        "FontColor": null,
        "FillColor": "#9C0006",
        "ColorScaleColorMinimum": null,
        "ColorScaleColorMaximum": null,
        "ContainsTextSearch": "CalendarRepairAssistant",
        "ContainsTextOperator": "Contains",
        "CellValueFormula1": null,
        "CellValueFormula2": null,
        "CellValueOperator": null,
        "CustomFormula": null
      }
  ],
  "filterDefinitions": [
    {
      "FilterActiveByUIOnly": false,
      "FilterKey": "LogonType123825",
      "FilterValue": "Owner",
      "ColumnName": "LogonType",
      "FriendlyName": "LogonType filter =Owner"
    }
  ]
}
